nlpturk/__init__.py
nlpturk-0.0.0a0.dist-info/LICENSE
nlpturk-0.0.0a0.dist-info/METADATA
nlpturk-0.0.0a0.dist-info/WHEEL
nlpturk-0.0.0a0.dist-info/entry_points.txt
nlpturk-0.0.0a0.dist-info/top_level.txt
nlpturk-0.0.0a0.dist-info/RECORD
