Metadata-Version: 2.1
Name: nlpturk
Version: 0.0.0a0
Summary: Turkish NLP library
Author-email: "Bedii A. Aydoğan" <nlpturk.ai@gmail.com>
License: MIT License
Project-URL: Homepage, https://github.com/nlpturk/nlpturk
Project-URL: Repository, https://github.com/nlpturk/nlpturk
Keywords: nlp,turkish
Classifier: License :: OSI Approved :: MIT License
Classifier: Programming Language :: Python
Classifier: Programming Language :: Python :: 3
Requires-Python: >=3.6
License-File: LICENSE
Requires-Dist: scikit-learn
Provides-Extra: build
Requires-Dist: build ; extra == 'build'
Requires-Dist: twine ; extra == 'build'
Provides-Extra: dev
Requires-Dist: pytest ; extra == 'dev'
